LICENSE
MANIFEST.in
README.md
setup.py
django_templatefield.egg-info/PKG-INFO
django_templatefield.egg-info/SOURCES.txt
django_templatefield.egg-info/dependency_links.txt
django_templatefield.egg-info/requires.txt
django_templatefield.egg-info/top_level.txt
templatefield/__init__.py
templatefield/fields.py
templatefield/models.py
templatefield/test_settings.py